setup.cfg
setup.py
googl/__init__.py
googl/googl.py
googl/short_url.py
googl.egg-info/PKG-INFO
googl.egg-info/SOURCES.txt
googl.egg-info/dependency_links.txt
googl.egg-info/entry_points.txt
googl.egg-info/not-zip-safe
googl.egg-info/requires.txt
googl.egg-info/top_level.txt