Metadata-Version: 1.0
Name: googl
Version: 0.1dev
Summary: Goo.gl API wrapper for Python.
Home-page: blog.douglascamata.net
Author: Douglas Camata
Author-email: d.camata@gmail.com
License: GPLv3
Keywords: goo.gl url shortener
Platform: UNKNOWN
